{
    "language": "en",
    "type": "lovers",
    "topicLabel": "🌶️🌶️🌶️ Authentic Love",
    "topicPath": "authentic_love",
    "spiceLevel": 3,
    "questions": [
        "What does authentic love mean to you?",
        "How do you define being truly yourself in a relationship?",
        "What fears do you have about showing your true self to me?",
        "How do you feel when I share my vulnerabilities with you?",
        "What does it mean to you to love someone without conditions?",
        "How do you navigate the balance between individuality and togetherness?",
        "What are the deepest truths about yourself that you want me to know?",
        "How do you feel when I accept you for who you are, flaws and all?",
        "What does it mean to you to feel completely seen in our relationship?",
        "How do you handle the fear of being judged for your true self?",
        "What are the ways you feel most loved and understood by me?",
        "How do you express your authentic self in our relationship?",
        "What does it mean to you to feel emotionally safe with me?",
        "How do you feel when I encourage you to be your true self?",
        "What are the parts of yourself that you find hardest to share with me?",
        "How do you navigate the fear of being vulnerable in love?",
        "What does it mean to you to love someone for who they truly are?",
        "How do you feel when I embrace your imperfections?",
        "What are the ways you show your love in the most genuine way?",
        "How do you handle the fear of not being enough for me?",
        "What does it mean to you to feel completely accepted in our relationship?",
        "How do you feel when I share my deepest fears with you?",
        "What are the ways you feel most connected to your true self?",
        "How do you navigate the challenges of being authentic in love?",
        "What does it mean to you to feel truly valued for who you are?",
        "How do you feel when I celebrate your uniqueness?",
        "What are the ways you express your love in the most honest way?",
        "How do you handle the fear of losing yourself in a relationship?",
        "What does it mean to you to feel emotionally aligned with me?",
        "How do you feel when I support your personal growth?",
        "What are the ways you show your love without holding back?",
        "How do you navigate the fear of being too much for me?",
        "What does it mean to you to feel completely understood in our relationship?",
        "How do you feel when I encourage you to pursue your passions?",
        "What are the ways you feel most free to be yourself with me?",
        "How do you handle the fear of being rejected for your true self?",
        "What does it mean to you to feel emotionally safe to be vulnerable?",
        "How do you feel when I accept you without trying to change you?",
        "What are the ways you express your love in the most authentic way?",
        "How do you navigate the fear of being misunderstood in love?",
        "What does it mean to you to feel completely loved for who you are?",
        "How do you feel when I honor your individuality in our relationship?",
        "What are the ways you feel most connected to your authentic self?",
        "How do you handle the fear of being seen as weak when you’re vulnerable?",
        "What does it mean to you to feel emotionally supported in our relationship?",
        "How do you feel when I show appreciation for your true self?",
        "What are the ways you express your love in the most genuine way?",
        "How do you navigate the fear of being too vulnerable with me?",
        "What does it mean to you to feel completely accepted for who you are?",
        "How do you feel when I encourage you to share your true feelings?",
        "What are the ways you feel most loved when you’re being yourself?",
        "How do you handle the fear of being judged for your imperfections?",
        "What does it mean to you to feel emotionally safe to be yourself?",
        "How do you feel when I embrace your true self without hesitation?",
        "What are the ways you express your love in the most honest way?",
        "How do you navigate the fear of being too open in our relationship?",
        "What does it mean to you to feel completely valued for who you are?",
        "How do you feel when I celebrate your authenticity?",
        "What are the ways you feel most connected to your true self with me?",
        "How do you handle the fear of being vulnerable in our relationship?",
        "What does it mean to you to feel emotionally aligned with me?",
        "How do you feel when I support your journey of self-discovery?",
        "What are the ways you show your love in the most authentic way?",
        "How do you navigate the fear of being too honest in love?",
        "What does it mean to you to feel completely understood by me?",
        "How do you feel when I encourage you to be unapologetically yourself?",
        "What are the ways you feel most free to express your true self?",
        "How do you handle the fear of being rejected for your authenticity?",
        "What does it mean to you to feel emotionally safe to share your truth?",
        "How do you feel when I accept you just as you are?",
        "What are the ways you express your love in the most genuine way?",
        "How do you navigate the fear of being too vulnerable in our relationship?",
        "What does it mean to you to feel completely loved for your true self?",
        "How do you feel when I honor your individuality in our love?",
        "What are the ways you feel most connected to your authentic self with me?",
        "How do you handle the fear of being seen as weak when you’re honest?",
        "What does it mean to you to feel emotionally supported in our love?",
        "How do you feel when I show appreciation for your true self?",
        "What are the ways you express your love in the most honest way?",
        "How do you navigate the fear of being too open with me?",
        "What does it mean to you to feel completely accepted for who you are?",
        "How do you feel when I encourage you to share your true feelings?",
        "What are the ways you feel most loved when you’re being yourself?",
        "How do you handle the fear of being judged for your imperfections?",
        "What does it mean to you to feel emotionally safe to be yourself?",
        "How do you feel when I embrace your true self without hesitation?",
        "What are the ways you express your love in the most authentic way?",
        "How do you navigate the fear of being too open in our relationship?",
        "What does it mean to you to feel completely valued for who you are?",
        "How do you feel when I celebrate your authenticity?",
        "What are the ways you feel most connected to your true self with me?",
        "How do you handle the fear of being vulnerable in our relationship?",
        "What does it mean to you to feel emotionally aligned with me?",
        "How do you feel when I support your journey of self-discovery?",
        "What are the ways you show your love in the most authentic way?",
        "How do you navigate the fear of being too honest in love?",
        "What does it mean to you to feel completely understood by me?",
        "How do you feel when I encourage you to be unapologetically yourself?",
        "What are the ways you feel most free to express your true self?",
        "How do you handle the fear of being rejected for your authenticity?",
        "What does it mean to you to feel emotionally safe to share your truth?",
        "How do you feel when I accept you just as you are?"
    ]
}
