{
    "language": "th",
    "type": "friends",
    "topicLabel": "🌶️🌶️ การเปลี่ยนชีวิต",
    "topicPath": "life_changes",
    "spiceLevel": 2,
    "questions": [
        "คุณเคยทำอะไรในชีวิตแล้วรู้สึกว่ามันเปลี่ยนคุณไปตลอดไหม?",
        "คุณเคยต้องตัดสินใจครั้งใหญ่ที่เปลี่ยนเส้นทางชีวิตไหม?",
        "คุณเคยเปลี่ยนงานหรือสายอาชีพแล้วรู้สึกดีไหม?",
        "คุณเคยต้องย้ายเมืองหรือประเทศเพื่อเริ่มชีวิตใหม่ไหม?",
        "คุณเคยเปลี่ยนความคิดหรือมุมมองชีวิตเพราะเหตุการณ์สำคัญไหม?",
        "คุณเคยเปลี่ยนความสัมพันธ์กับใครบางคนเพราะชีวิตเปลี่ยนไหม?",
        "คุณเคยเริ่มทำอะไรใหม่ๆ ที่ทำให้ชีวิตคุณสดชื่นขึ้นไหม?",
        "คุณเคยต้องละทิ้งบางสิ่งเพื่อเริ่มต้นชีวิตใหม่ไหม?",
        "คุณเคยเปลี่ยนตัวเองเพื่อให้เข้ากับสถานการณ์ใหม่ไหม?",
        "คุณเคยรู้สึกกลัวแต่ก็กล้าที่จะเปลี่ยนชีวิตไหม?",
        "คุณเคยเปลี่ยนความคิดเรื่องความรักหรือมิตรภาพไหม?",
        "คุณเคยเปลี่ยนความสนใจหรืองานอดิเรกที่ทำให้ชีวิตมีสีสันไหม?",
        "คุณเคยรู้สึกว่าการเปลี่ยนแปลงทำให้คุณเติบโตมากขึ้นไหม?",
        "คุณเคยเปลี่ยนความคิดเกี่ยวกับความสำเร็จหลังจากเหตุการณ์ใหญ่ไหม?",
        "คุณเคยต้องปรับตัวกับการเปลี่ยนแปลงที่ไม่คาดคิดไหม?",
        "คุณเคยเปลี่ยนแผนชีวิตเพราะเจออุปสรรคใหญ่ไหม?",
        "คุณเคยเปลี่ยนสิ่งเล็กๆ ในชีวิตแต่มีผลกระทบใหญ่ไหม?",
        "คุณเคยต้องปล่อยวางบางสิ่งเพื่อก้าวไปข้างหน้าไหม?",
        "คุณเคยเปลี่ยนทัศนคติเรื่องความสุขเพราะชีวิตเปลี่ยนไหม?",
        "คุณเคยปรับตัวเข้ากับชีวิตใหม่และรู้สึกภูมิใจไหม?",
        "คุณเคยต้องเปลี่ยนความคาดหวังจากตัวเองหรือคนอื่นไหม?",
        "คุณเคยเปลี่ยนสภาพแวดล้อมเพราะอยากชีวิตดีขึ้นไหม?",
        "คุณเคยเริ่มต้นความสัมพันธ์ใหม่หลังจากเปลี่ยนชีวิตไหม?",
        "คุณเคยเปลี่ยนวิธีคิดเรื่องความล้มเหลวไหม?",
        "คุณเคยต้องเปลี่ยนตัวเองเพื่อโอกาสใหม่ๆ ในชีวิตไหม?",
        "คุณเคยปรับเปลี่ยนความคิดเรื่องความสำเร็จหลังจากพลาดอะไรไหม?",
        "คุณเคยเปลี่ยนสิ่งเล็กๆ ที่ทำให้ชีวิตดีขึ้นไหม?",
        "คุณเคยต้องเปลี่ยนพฤติกรรมบางอย่างเพื่อชีวิตที่สงบขึ้นไหม?",
        "คุณเคยเปลี่ยนทัศนคติเรื่องการทำงานหรือเรียนไหม?",
        "คุณเคยต้องเปลี่ยนความเชื่อหรือค่านิยมเพราะสถานการณ์ไหม?",
        "คุณเคยเปลี่ยนตัวเองเพื่อให้เข้ากับเพื่อนหรือครอบครัวไหม?",
        "คุณเคยเริ่มต้นชีวิตใหม่หลังจากเหตุการณ์ที่ทำให้คุณเจ็บปวดไหม?",
        "คุณเคยเปลี่ยนความคิดเรื่องอนาคตหลังจากประสบการณ์หนักไหม?",
        "คุณเคยปรับตัวกับชีวิตใหม่ที่ไม่เหมือนเดิมไหม?",
        "คุณเคยต้องเปลี่ยนตัวเองเพื่อให้โอกาสดีๆ ผ่านเข้ามาไหม?",
        "คุณเคยเปลี่ยนสิ่งเล็กๆ ในชีวิตแต่ทำให้คุณมีความสุขมากขึ้นไหม?",
        "คุณเคยต้องเปลี่ยนความคิดเรื่องตัวเองเพื่อเข้าใจคนอื่นไหม?",
        "คุณเคยเปลี่ยนกิจวัตรประจำวันที่ทำให้ชีวิตง่ายขึ้นไหม?",
        "คุณเคยต้องเปลี่ยนเป้าหมายเพราะสิ่งที่เกิดขึ้นในชีวิตไหม?",
        "คุณเคยเริ่มต้นชีวิตใหม่ที่ทำให้คุณกลัวแต่ตื่นเต้นไหม?",
        "คุณเคยเปลี่ยนตัวเองเพื่อโอกาสทางความรักไหม?",
        "คุณเคยเปลี่ยนความคิดเรื่องอดีตเพื่อตั้งใจอนาคตไหม?",
        "คุณเคยปรับตัวกับสิ่งที่ไม่คาดคิดในชีวิตและสำเร็จไหม?",
        "คุณเคยเปลี่ยนทัศนคติเรื่องความรักหรือมิตรภาพไหม?",
        "คุณเคยต้องเปลี่ยนตัวเองเพื่อทำตามความฝันไหม?",
        "คุณเคยเปลี่ยนสิ่งรอบตัวเพื่อสร้างชีวิตที่คุณอยากมีไหม?",
        "คุณเคยเริ่มต้นชีวิตใหม่หลังจากสูญเสียอะไรสำคัญไหม?",
        "คุณเคยเปลี่ยนความคิดเรื่องความผิดพลาดเพื่อเรียนรู้ไหม?",
        "คุณเคยต้องเปลี่ยนความเชื่อเพื่อให้ชีวิตเดินต่อไหม?",
        "คุณเคยเปลี่ยนวิธีคิดเรื่องความสำเร็จหรือความล้มเหลวไหม?",
        "คุณเคยปรับตัวเพื่อชีวิตที่สบายขึ้นหลังจากเปลี่ยนอะไรบางอย่างไหม?",
        "คุณเคยเปลี่ยนทัศนคติเรื่องความสุขเพราะประสบการณ์ไหม?",
        "คุณเคยต้องเปลี่ยนตัวเองเพื่ออยู่กับคนรอบข้างได้ดีขึ้นไหม?",
        "คุณเคยเปลี่ยนความคิดเรื่องเป้าหมายชีวิตเพราะเหตุการณ์สำคัญไหม?",
        "คุณเคยต้องปรับตัวกับชีวิตใหม่ที่ทำให้คุณท้าทายตัวเองไหม?",
        "คุณเคยเปลี่ยนตัวเองเพื่อให้โอกาสงานหรือการเรียนดีขึ้นไหม?",
        "คุณเคยเปลี่ยนกิจวัตรเล็กๆ ในชีวิตแล้วรู้สึกดีขึ้นไหม?",
        "คุณเคยต้องเปลี่ยนความคิดเรื่องความรักหรือมิตรภาพไหม?",
        "คุณเคยเริ่มต้นชีวิตใหม่ด้วยความกลัวแต่ก็กล้าลองไหม?",
        "คุณเคยเปลี่ยนตัวเองเพื่อปรับชีวิตให้สมดุลไหม?",
        "คุณเคยเปลี่ยนสิ่งที่ทำทุกวันเพื่อชีวิตที่มีความสุขขึ้นไหม?",
        "คุณเคยต้องเปลี่ยนทัศนคติเรื่องความสำเร็จหรือความล้มเหลวไหม?",
        "คุณเคยปรับตัวเข้ากับชีวิตใหม่และรู้สึกภูมิใจไหม?",
        "คุณเคยต้องเปลี่ยนตัวเองเพื่อโอกาสใหม่ในชีวิตไหม?",
        "คุณเคยเปลี่ยนกิจวัตรประจำวันที่ทำให้ชีวิตง่ายขึ้นไหม?",
        "คุณเคยเริ่มต้นชีวิตใหม่ที่ทำให้คุณตื่นเต้นและกลัวพร้อมกันไหม?",
        "คุณเคยเปลี่ยนตัวเองเพื่อให้เข้ากับคนรอบตัวไหม?",
        "คุณเคยต้องเปลี่ยนความคิดเรื่องอดีตเพื่อเดินหน้าชีวิตไหม?",
        "คุณเคยปรับตัวเข้ากับสถานการณ์ใหม่แล้วรู้สึกประสบความสำเร็จไหม?",
        "คุณเคยเปลี่ยนความคิดเรื่องความผิดพลาดเพื่อเรียนรู้และเติบโตไหม?",
        "คุณเคยต้องเปลี่ยนตัวเองเพื่อทำตามความฝันหรือเป้าหมายไหม?",
        "คุณเคยเปลี่ยนสิ่งรอบตัวเพื่อชีวิตที่ดีขึ้นไหม?",
        "คุณเคยเริ่มต้นชีวิตใหม่หลังจากสูญเสียสิ่งสำคัญไหม?",
        "คุณเคยเปลี่ยนความคิดเรื่องความรักหรือมิตรภาพเพื่อเติบโตไหม?",
        "คุณเคยต้องปรับตัวกับชีวิตใหม่ที่ทำให้ท้าทายตัวเองไหม?",
        "คุณเคยเปลี่ยนทัศนคติเรื่องความสุขหลังจากประสบการณ์สำคัญไหม?",
        "คุณเคยเปลี่ยนตัวเองเพื่อให้โอกาสงานหรือการเรียนดีขึ้นไหม?",
        "คุณเคยเปลี่ยนกิจวัตรเล็กๆ แล้วรู้สึกว่าชีวิตดีขึ้นไหม?",
        "คุณเคยต้องเปลี่ยนความคิดเรื่องความสำเร็จหรือความล้มเหลวไหม?",
        "คุณเคยปรับตัวเข้ากับชีวิตใหม่และรู้สึกภูมิใจไหม?",
        "คุณเคยต้องเปลี่ยนตัวเองเพื่อโอกาสใหม่ในชีวิตไหม?",
        "คุณเคยเปลี่ยนกิจวัตรประจำวันที่ทำให้ชีวิตง่ายขึ้นไหม?",
        "คุณเคยเริ่มต้นชีวิตใหม่ที่ทำให้คุณตื่นเต้นและกลัวพร้อมกันไหม?",
        "คุณเคยเปลี่ยนตัวเองเพื่อให้เข้ากับคนรอบตัวไหม?",
        "คุณเคยต้องเปลี่ยนความคิดเรื่องอดีตเพื่อเดินหน้าชีวิตไหม?",
        "คุณเคยปรับตัวเข้ากับสถานการณ์ใหม่แล้วรู้สึกประสบความสำเร็จไหม?",
        "คุณเคยเปลี่ยนความคิดเรื่องความผิดพลาดเพื่อเรียนรู้และเติบโตไหม?",
        "คุณเคยต้องเปลี่ยนตัวเองเพื่อทำตามความฝันหรือเป้าหมายไหม?",
        "คุณเคยเปลี่ยนสิ่งรอบตัวเพื่อชีวิตที่ดีขึ้นไหม?",
        "คุณเคยเริ่มต้นชีวิตใหม่หลังจากสูญเสียสิ่งสำคัญไหม?",
        "คุณเคยเปลี่ยนความคิดเรื่องความรักหรือมิตรภาพเพื่อเติบโตไหม?",
        "คุณเคยต้องปรับตัวกับชีวิตใหม่ที่ทำให้ท้าทายตัวเองไหม?",
        "คุณเคยเปลี่ยนทัศนคติเรื่องความสุขหลังจากประสบการณ์สำคัญไหม?",
        "คุณเคยเปลี่ยนตัวเองเพื่อให้โอกาสงานหรือการเรียนดีขึ้นไหม?",
        "คุณเคยเปลี่ยนกิจวัตรเล็กๆ แล้วรู้สึกว่าชีวิตดีขึ้นไหม?",
        "คุณเคยต้องเปลี่ยนความคิดเรื่องความสำเร็จหรือความล้มเหลวไหม?",
        "คุณเคยปรับตัวเข้ากับชีวิตใหม่และรู้สึกภูมิใจไหม?",
        "คุณเคยต้องเปลี่ยนตัวเองเพื่อโอกาสใหม่ในชีวิตไหม?"
    ]
}
